LICENCE.txt
README.md
setup.py
nait/__init__.py
nait/__main__.py
nait.egg-info/PKG-INFO
nait.egg-info/SOURCES.txt
nait.egg-info/dependency_links.txt
nait.egg-info/top_level.txt