Metadata-Version: 2.1
Name: nait
Version: 3.0.5
Summary: Neural network library
Home-page: UNKNOWN
Author: DanishDeveloper
License: MIT
Keywords: nait
Platform: UNKNOWN
Classifier: Development Status :: 5 - Production/Stable
Classifier: Intended Audience :: Education
Classifier: Operating System :: Microsoft :: Windows :: Windows 10
Classifier: License :: OSI Approved :: MIT License
Classifier: Programming Language :: Python :: 3
License-File: LICENCE.txt
